odoo10_addon_medical_base_us-10.0.1.0.0-py2.7-nspkg.pth
odoo/addons/medical_base_us/README.rst
odoo/addons/medical_base_us/__init__.py
odoo/addons/medical_base_us/__manifest__.py
odoo/addons/medical_base_us/data/res_partner_id_category.xml
odoo/addons/medical_base_us/i18n/es_CO.po
odoo/addons/medical_base_us/i18n/pt_BR.po
odoo/addons/medical_base_us/models/__init__.py
odoo/addons/medical_base_us/models/medical_abstract_dea.py
odoo/addons/medical_base_us/models/medical_abstract_luhn.py
odoo/addons/medical_base_us/models/medical_abstract_npi.py
odoo/addons/medical_base_us/static/description/icon.png
odoo/addons/medical_base_us/tests/__init__.py
odoo/addons/medical_base_us/tests/test_medical_dea_abstract.py
odoo/addons/medical_base_us/tests/test_medical_luhn_abstract.py
odoo/addons/medical_base_us/tests/test_medical_npi_abstract.py
odoo10_addon_medical_base_us-10.0.1.0.0.dist-info/DESCRIPTION.rst
odoo10_addon_medical_base_us-10.0.1.0.0.dist-info/METADATA
odoo10_addon_medical_base_us-10.0.1.0.0.dist-info/RECORD
odoo10_addon_medical_base_us-10.0.1.0.0.dist-info/WHEEL
odoo10_addon_medical_base_us-10.0.1.0.0.dist-info/metadata.json
odoo10_addon_medical_base_us-10.0.1.0.0.dist-info/namespace_packages.txt
odoo10_addon_medical_base_us-10.0.1.0.0.dist-info/top_level.txt
