Metadata-Version: 2.0
Name: odoo10-addon-medical-base-us
Version: 10.0.1.0.0
Summary: Provides some helper mixins for US locale
Home-page: https://github.com/OCA/vertical-medical
Author: LasLabs, Odoo Community Association (OCA)
Author-email: support@odoo-community.org
License: AGPL-3
Platform: UNKNOWN
Classifier: Programming Language :: Python
Classifier: Framework :: Odoo
Classifier: License :: OSI Approved :: GNU Affero General Public License v3
Requires-Python: ~=2.7
Requires-Dist: odoo (<10.1dev,>=10.0)
Requires-Dist: odoo10-addon-medical-agpl
